mangodb_connect/__init__.py
mangodb_connect/mongo_crud.py
MyDatabaseMongo-0.0.10.dist-info/LICENSE
MyDatabaseMongo-0.0.10.dist-info/METADATA
MyDatabaseMongo-0.0.10.dist-info/WHEEL
MyDatabaseMongo-0.0.10.dist-info/top_level.txt
MyDatabaseMongo-0.0.10.dist-info/RECORD
